chaostoxi/__init__.py
chaostoxi/toxiproxyapi.py
chaostoxi/proxy/__init__.py
chaostoxi/proxy/actions.py
chaostoxi/proxy/probes.py
chaostoxi/toxic/__init__.py
chaostoxi/toxic/actions.py
chaostoolkit_toxiproxy-0.3.1.dist-info/LICENSE
chaostoolkit_toxiproxy-0.3.1.dist-info/METADATA
chaostoolkit_toxiproxy-0.3.1.dist-info/WHEEL
chaostoolkit_toxiproxy-0.3.1.dist-info/top_level.txt
chaostoolkit_toxiproxy-0.3.1.dist-info/RECORD
